README.md
setup.cfg
setup.py
APIQrCode/__init__.py
APIQrCode/constants.py
APIQrCode/environment.py
APIQrCode/qrcode_cielo.py
APIQrCode.egg-info/PKG-INFO
APIQrCode.egg-info/SOURCES.txt
APIQrCode.egg-info/dependency_links.txt
APIQrCode.egg-info/requires.txt
APIQrCode.egg-info/top_level.txt
APIQrCode/request/__init__.py
APIQrCode/request/error.py
APIQrCode/request/get_access_token.py
APIQrCode/request/get_public_key.py
APIQrCode/request/parse_qrcode.py
APIQrCode/request/payment_card.py
APIQrCode/request/rsa_cryptography.py
tests/__init__.py
tests/test_constants.py
tests/test_environment.py
tests/test_qrcode_cielo.py