Metadata-Version: 2.1
Name: APIQrCode
Version: 1.0.6
Summary: SDK API QrCode Python Cielo
Home-page: https://github.com/Jeitto/sdk-qrcode-cielo.git
Author: Júnior Carvalho
Author-email: joseadolfojr@gmail.com
License: MIT
Keywords: cielo qrcode
Platform: UNKNOWN
Classifier: Intended Audience :: Developers
Classifier: Natural Language :: English
Classifier: License :: OSI Approved :: MIT License
Classifier: Programming Language :: Python
Classifier: Programming Language :: Python :: 3
Classifier: Topic :: Software Development :: Libraries
Requires-Python: >=3.0
